s360tools/__init__.py
s360tools/logger/__init__.py
s360tools/logger/errormessenger.py
s360tools/sheets/__init__.py
s360tools/sheets/sheethandler.py
s360tools-0.1.14.dist-info/LICENSE.txt
s360tools-0.1.14.dist-info/METADATA
s360tools-0.1.14.dist-info/WHEEL
s360tools-0.1.14.dist-info/top_level.txt
s360tools-0.1.14.dist-info/RECORD
